mineer/__init__.py
mineer/download_test_files.py
mineer/mineer.py
mineer/pipeline.py
mineer/utils.py
mineer/viz.py
mineer-0.6.0.dist-info/LICENSE
mineer-0.6.0.dist-info/METADATA
mineer-0.6.0.dist-info/WHEEL
mineer-0.6.0.dist-info/entry_points.txt
mineer-0.6.0.dist-info/top_level.txt
mineer-0.6.0.dist-info/RECORD
