Metadata-Version: 2.1
Name: mineer
Version: 0.6.0
Summary: Automated sequence truncation algorithm
Home-page: UNKNOWN
Author: michaelsilverstein
Author-email: michael.silverstein4@gmail.com
License: MIT
Platform: UNKNOWN
Requires-Python: >=3.8
License-File: LICENSE
Requires-Dist: numpy
Requires-Dist: pandas
Requires-Dist: seaborn
Requires-Dist: numba
Requires-Dist: joblib
Requires-Dist: dnaio
